process_nwb/__init__.py
process_nwb/common_referencing.py
process_nwb/linenoise_notch.py
process_nwb/resample.py
process_nwb/utils.py
process_nwb/wavelet_transform.py
process_nwb-0.1.4.data/scripts/preprocess_folder
process_nwb-0.1.4.dist-info/METADATA
process_nwb-0.1.4.dist-info/WHEEL
process_nwb-0.1.4.dist-info/top_level.txt
process_nwb-0.1.4.dist-info/RECORD
