Metadata-Version: 2.1
Name: process-nwb
Version: 0.1.4
Summary: ECoG preprocessing scripts for NWB files.
Home-page: UNKNOWN
Author: Jesse Livezey
Author-email: jesse.livezey@gmail.com
License: UNKNOWN
Platform: UNKNOWN
Requires-Dist: numpy
Requires-Dist: scipy
Requires-Dist: pynwb
